zenmodel/__init__.py
zenmodel/brain_context.py
zenmodel/processor.py
zenmodel/selector.py
zenmodel-0.1.13.dist-info/METADATA
zenmodel-0.1.13.dist-info/WHEEL
zenmodel-0.1.13.dist-info/top_level.txt
zenmodel-0.1.13.dist-info/RECORD
