Metadata-Version: 2.1
Name: zenmodel
Version: 0.1.13
Summary: A Python processor for ZenModel
Home-page: https://github.com/zenmodel/zenmodel
Author: Clay
Author-email: clay.zhang@outlook.com
Classifier: Programming Language :: Python :: 3
Classifier: License :: OSI Approved :: MIT License
Classifier: Operating System :: OS Independent
Requires-Python: >=3.6
